akamai_papi/__init__.py
akamai_papi/client.py
akamai_papi/exceptions.py
akamai_papi/utils.py
akamai_papi-0.1.2.dist-info/licenses/LICENSE
akamai_papi-0.1.2.dist-info/METADATA
akamai_papi-0.1.2.dist-info/WHEEL
akamai_papi-0.1.2.dist-info/top_level.txt
akamai_papi-0.1.2.dist-info/RECORD
