Metadata-Version: 2.4
Name: akamai-papi
Version: 0.1.2
Summary: SDK for Akamai Property Manager API (PAPI)
Author: Akamai
License: MIT License
Project-URL: Homepage, https://github.com/akamai-packages/akamai-papi
Project-URL: Documentation, https://akamai-packages.github.io/akamai-papi
Project-URL: Repository, https://github.com/akamai-packages/akamai-papi
Project-URL: Issues, https://github.com/akamai-packages/akamai-papi/issues
Requires-Python: >=3.6
License-File: LICENSE
Requires-Dist: requests
Requires-Dist: edgegrid-python
Dynamic: license-file
